{"category_slug":"librer_a","subcategory_slug":"","page":131,"page_size":48,"total":9412,"items":[{"id":"LA-952185","nombre":"MARCADOR UNI POSCA PC-5M PTA MEDIA DAMASCO","categoria":"Librería","subcategoria":"","precio":5335.78,"destacado":false,"descripcion":"","imagen":"assets/products/LA-952185.webp","tags":["marcador","uni","posca","pta","media","damasco"]},{"id":"LA-952195","nombre":"MARCADOR UNI POSCA PC-5M PTA MEDIA FUCSIA","categoria":"Librería","subcategoria":"","precio":5335.78,"destacado":false,"descripcion":"","imagen":"assets/products/LA-952195.webp","tags":["marcador","uni","posca","pta","media","fucsia"]},{"id":"LA-952190","nombre":"MARCADOR UNI POSCA PC-5M PTA MEDIA GRIS","categoria":"Librería","subcategoria":"","precio":5335.78,"destacado":false,"descripcion":"","imagen":"assets/products/LA-952190.webp","tags":["marcador","uni","posca","pta","media","gris"]},{"id":"LA-952188","nombre":"MARCADOR UNI POSCA PC-5M PTA MEDIA LAVANDA","categoria":"Librería","subcategoria":"","precio":5335.78,"destacado":false,"descripcion":"","imagen":"assets/products/LA-952188.webp","tags":["marcador","uni","posca","pta","media","lavanda"]},{"id":"LA-952192","nombre":"MARCADOR UNI POSCA PC-5M PTA MEDIA LILA","categoria":"Librería","subcategoria":"","precio":5335.78,"destacado":false,"descripcion":"","imagen":"assets/products/LA-952192.webp","tags":["marcador","uni","posca","pta","media","lila"]},{"id":"LA-952189","nombre":"MARCADOR UNI POSCA PC-5M PTA MEDIA MARFIL","categoria":"Librería","subcategoria":"","precio":5335.78,"destacado":false,"descripcion":"","imagen":"assets/products/LA-952189.webp","tags":["marcador","uni","posca","pta","media","marfil"]},{"id":"LA-952191","nombre":"MARCADOR UNI POSCA PC-5M PTA MEDIA MARRON","categoria":"Librería","subcategoria":"","precio":5335.78,"destacado":false,"descripcion":"","imagen":"assets/products/LA-952191.webp","tags":["marcador","uni","posca","pta","media","marron"]},{"id":"LA-952196","nombre":"MARCADOR UNI POSCA PC-5M PTA MEDIA MARRON OSCURO","categoria":"Librería","subcategoria":"","precio":5335.78,"destacado":false,"descripcion":"","imagen":"assets/products/LA-952196.webp","tags":["marcador","uni","posca","pta","media","marron","oscuro"]},{"id":"LA-952183","nombre":"MARCADOR UNI POSCA PC-5M PTA MEDIA NARANJA","categoria":"Librería","subcategoria":"","precio":5335.78,"destacado":false,"descripcion":"","imagen":"assets/products/LA-952183.webp","tags":["marcador","uni","posca","pta","media","naranja"]},{"id":"LA-952184","nombre":"MARCADOR UNI POSCA PC-5M PTA MEDIA NARANJA CLARO/PALIDO","categoria":"Librería","subcategoria":"","precio":5335.78,"destacado":false,"descripcion":"","imagen":"assets/products/LA-952184.webp","tags":["marcador","uni","posca","pta","media","naranja","claro","palido"]},{"id":"LA-952211","nombre":"MARCADOR UNI POSCA PC-5M PTA MEDIA NARANJA FLUO","categoria":"Librería","subcategoria":"","precio":5335.78,"destacado":false,"descripcion":"","imagen":"assets/products/LA-952211.webp","tags":["marcador","uni","posca","pta","media","naranja","fluo"]},{"id":"LA-952175","nombre":"MARCADOR UNI POSCA PC-5M PTA MEDIA NEGRO","categoria":"Librería","subcategoria":"","precio":5335.78,"destacado":false,"descripcion":"","imagen":"assets/products/LA-952175.webp","tags":["marcador","uni","posca","pta","media","negro"]},{"id":"LA-952170","nombre":"MARCADOR UNI POSCA PC-5M PTA MEDIA ORO","categoria":"Librería","subcategoria":"","precio":5335.78,"destacado":false,"descripcion":"","imagen":"assets/products/LA-952170.webp","tags":["marcador","uni","posca","pta","media","oro"]},{"id":"LA-952171","nombre":"MARCADOR UNI POSCA PC-5M PTA MEDIA PLATA","categoria":"Librería","subcategoria":"","precio":5335.78,"destacado":false,"descripcion":"","imagen":"assets/products/LA-952171.webp","tags":["marcador","uni","posca","pta","media","plata"]},{"id":"LA-952176","nombre":"MARCADOR UNI POSCA PC-5M PTA MEDIA ROJO","categoria":"Librería","subcategoria":"","precio":5335.78,"destacado":false,"descripcion":"","imagen":"assets/products/LA-952176.webp","tags":["marcador","uni","posca","pta","media","rojo"]},{"id":"LA-952197","nombre":"MARCADOR UNI POSCA PC-5M PTA MEDIA ROJO OSCURO","categoria":"Librería","subcategoria":"","precio":5335.78,"destacado":false,"descripcion":"","imagen":"assets/products/LA-952197.webp","tags":["marcador","uni","posca","pta","media","rojo","oscuro"]},{"id":"LA-952181","nombre":"MARCADOR UNI POSCA PC-5M PTA MEDIA ROSA","categoria":"Librería","subcategoria":"","precio":5335.78,"destacado":false,"descripcion":"","imagen":"assets/products/LA-952181.webp","tags":["marcador","uni","posca","pta","media","rosa"]},{"id":"LA-952182","nombre":"MARCADOR UNI POSCA PC-5M PTA MEDIA ROSA CLARO","categoria":"Librería","subcategoria":"","precio":5335.78,"destacado":false,"descripcion":"","imagen":"assets/products/LA-952182.webp","tags":["marcador","uni","posca","pta","media","rosa","claro"]},{"id":"LA-952212","nombre":"MARCADOR UNI POSCA PC-5M PTA MEDIA ROSA FLUO","categoria":"Librería","subcategoria":"","precio":5335.78,"destacado":false,"descripcion":"","imagen":"assets/products/LA-952212.webp","tags":["marcador","uni","posca","pta","media","rosa","fluo"]},{"id":"LA-952169","nombre":"MARCADOR UNI POSCA PC-5M PTA MEDIA V/COLORES","categoria":"Librería","subcategoria":"","precio":5335.78,"destacado":false,"descripcion":"","imagen":"assets/products/LA-952169.webp","tags":["marcador","uni","posca","pta","media","colores"]},{"id":"LA-952177","nombre":"MARCADOR UNI POSCA PC-5M PTA MEDIA VERDE","categoria":"Librería","subcategoria":"","precio":5335.78,"destacado":false,"descripcion":"","imagen":"assets/products/LA-952177.webp","tags":["marcador","uni","posca","pta","media","verde"]},{"id":"LA-952198","nombre":"MARCADOR UNI POSCA PC-5M PTA MEDIA VERDE AGUA/MARINO","categoria":"Librería","subcategoria":"","precio":5335.78,"destacado":false,"descripcion":"","imagen":"assets/products/LA-952198.webp","tags":["marcador","uni","posca","pta","media","verde","agua","marino"]},{"id":"LA-952178","nombre":"MARCADOR UNI POSCA PC-5M PTA MEDIA VERDE CLARO","categoria":"Librería","subcategoria":"","precio":5335.78,"destacado":false,"descripcion":"","imagen":"assets/products/LA-952178.webp","tags":["marcador","uni","posca","pta","media","verde","claro"]},{"id":"LA-952180","nombre":"MARCADOR UNI POSCA PC-5M PTA MEDIA VERDE ESMERALDA","categoria":"Librería","subcategoria":"","precio":5335.78,"destacado":false,"descripcion":"","imagen":"assets/products/LA-952180.webp","tags":["marcador","uni","posca","pta","media","verde","esmeralda"]},{"id":"LA-952193","nombre":"MARCADOR UNI POSCA PC-5M PTA MEDIA VERDE KHAKI","categoria":"Librería","subcategoria":"","precio":5335.78,"destacado":false,"descripcion":"","imagen":"assets/products/LA-952193.webp","tags":["marcador","uni","posca","pta","media","verde","khaki"]},{"id":"LA-952179","nombre":"MARCADOR UNI POSCA PC-5M PTA MEDIA VERDE MANZANA","categoria":"Librería","subcategoria":"","precio":5335.78,"destacado":false,"descripcion":"","imagen":"assets/products/LA-952179.webp","tags":["marcador","uni","posca","pta","media","verde","manzana"]},{"id":"LA-952187","nombre":"MARCADOR UNI POSCA PC-5M PTA MEDIA VIOLETA","categoria":"Librería","subcategoria":"","precio":5335.78,"destacado":false,"descripcion":"","imagen":"assets/products/LA-952187.webp","tags":["marcador","uni","posca","pta","media","violeta"]},{"id":"LA-952235","nombre":"MARCADOR UNI POSCA PC-5M WALLET X 12 U.","categoria":"Librería","subcategoria":"","precio":79437.79,"destacado":false,"descripcion":"","imagen":"assets/products/LA-952235.webp","tags":["marcador","uni","posca","wallet"]},{"id":"LA-952266","nombre":"MARCADOR UNI POSCA PC-8K PTA. CHANFLEADA AMARILLO","categoria":"Librería","subcategoria":"","precio":7050.16,"destacado":false,"descripcion":"","imagen":"assets/products/LA-952266.webp","tags":["marcador","uni","posca","pta","chanfleada","amarillo"]},{"id":"LA-952290","nombre":"MARCADOR UNI POSCA PC-8K PTA. CHANFLEADA AMARILLO FLUO","categoria":"Librería","subcategoria":"","precio":7050.16,"destacado":false,"descripcion":"","imagen":"assets/products/LA-952290.webp","tags":["marcador","uni","posca","pta","chanfleada","amarillo","fluo"]},{"id":"LA-952253","nombre":"MARCADOR UNI POSCA PC-8K PTA. CHANFLEADA AZUL","categoria":"Librería","subcategoria":"","precio":7050.16,"destacado":false,"descripcion":"","imagen":"assets/products/LA-952253.webp","tags":["marcador","uni","posca","pta","chanfleada","azul"]},{"id":"LA-952252","nombre":"MARCADOR UNI POSCA PC-8K PTA. CHANFLEADA BLANCO","categoria":"Librería","subcategoria":"","precio":7050.16,"destacado":false,"descripcion":"","imagen":"assets/products/LA-952252.webp","tags":["marcador","uni","posca","pta","chanfleada","blanco"]},{"id":"LA-952254","nombre":"MARCADOR UNI POSCA PC-8K PTA. CHANFLEADA CELESTE","categoria":"Librería","subcategoria":"","precio":7050.16,"destacado":false,"descripcion":"","imagen":"assets/products/LA-952254.webp","tags":["marcador","uni","posca","pta","chanfleada","celeste"]},{"id":"LA-952271","nombre":"MARCADOR UNI POSCA PC-8K PTA. CHANFLEADA MARRON","categoria":"Librería","subcategoria":"","precio":7050.16,"destacado":false,"descripcion":"","imagen":"assets/products/LA-952271.webp","tags":["marcador","uni","posca","pta","chanfleada","marron"]},{"id":"LA-952264","nombre":"MARCADOR UNI POSCA PC-8K PTA. CHANFLEADA NARANJA","categoria":"Librería","subcategoria":"","precio":7050.16,"destacado":false,"descripcion":"","imagen":"assets/products/LA-952264.webp","tags":["marcador","uni","posca","pta","chanfleada","naranja"]},{"id":"LA-952255","nombre":"MARCADOR UNI POSCA PC-8K PTA. CHANFLEADA NEGRO","categoria":"Librería","subcategoria":"","precio":7050.16,"destacado":false,"descripcion":"","imagen":"assets/products/LA-952255.webp","tags":["marcador","uni","posca","pta","chanfleada","negro"]},{"id":"LA-952250","nombre":"MARCADOR UNI POSCA PC-8K PTA. CHANFLEADA ORO","categoria":"Librería","subcategoria":"","precio":7050.16,"destacado":false,"descripcion":"","imagen":"assets/products/LA-952250.webp","tags":["marcador","uni","posca","pta","chanfleada","oro"]},{"id":"LA-952251","nombre":"MARCADOR UNI POSCA PC-8K PTA. CHANFLEADA PLATA","categoria":"Librería","subcategoria":"","precio":7050.16,"destacado":false,"descripcion":"","imagen":"assets/products/LA-952251.webp","tags":["marcador","uni","posca","pta","chanfleada","plata"]},{"id":"LA-952256","nombre":"MARCADOR UNI POSCA PC-8K PTA. CHANFLEADA ROJO","categoria":"Librería","subcategoria":"","precio":7050.16,"destacado":false,"descripcion":"","imagen":"assets/products/LA-952256.webp","tags":["marcador","uni","posca","pta","chanfleada","rojo"]},{"id":"LA-952261","nombre":"MARCADOR UNI POSCA PC-8K PTA. CHANFLEADA ROSA","categoria":"Librería","subcategoria":"","precio":7050.16,"destacado":false,"descripcion":"","imagen":"assets/products/LA-952261.webp","tags":["marcador","uni","posca","pta","chanfleada","rosa"]},{"id":"LA-952291","nombre":"MARCADOR UNI POSCA PC-8K PTA. CHANFLEADA ROSA FLUO","categoria":"Librería","subcategoria":"","precio":7050.16,"destacado":false,"descripcion":"","imagen":"assets/products/LA-952291.webp","tags":["marcador","uni","posca","pta","chanfleada","rosa","fluo"]},{"id":"LA-952249","nombre":"MARCADOR UNI POSCA PC-8K PTA. CHANFLEADA V/COLORES","categoria":"Librería","subcategoria":"","precio":7050.16,"destacado":false,"descripcion":"","imagen":"assets/products/LA-952249.webp","tags":["marcador","uni","posca","pta","chanfleada","colores"]},{"id":"LA-952257","nombre":"MARCADOR UNI POSCA PC-8K PTA. CHANFLEADA VERDE","categoria":"Librería","subcategoria":"","precio":7050.16,"destacado":false,"descripcion":"","imagen":"assets/products/LA-952257.webp","tags":["marcador","uni","posca","pta","chanfleada","verde"]},{"id":"LA-952258","nombre":"MARCADOR UNI POSCA PC-8K PTA. CHANFLEADA VERDE CLARO","categoria":"Librería","subcategoria":"","precio":7050.16,"destacado":false,"descripcion":"","imagen":"assets/products/LA-952258.webp","tags":["marcador","uni","posca","pta","chanfleada","verde","claro"]},{"id":"LA-952292","nombre":"MARCADOR UNI POSCA PC-8K PTA. CHANFLEADA VERDE FLUO","categoria":"Librería","subcategoria":"","precio":7050.16,"destacado":false,"descripcion":"","imagen":"assets/products/LA-952292.webp","tags":["marcador","uni","posca","pta","chanfleada","verde","fluo"]},{"id":"LA-952349","nombre":"MARCADOR UNI POSCA PCF-350 PTA PINCEL V/COLORES","categoria":"Librería","subcategoria":"","precio":10506.28,"destacado":false,"descripcion":"","imagen":"assets/products/LA-952349.webp","tags":["marcador","uni","posca","pcf","350","pta","pincel","colores"]},{"id":"LA-952366","nombre":"MARCADOR UNI POSCA PCF-350 PTA. PINCEL AMARILLO","categoria":"Librería","subcategoria":"","precio":10506.28,"destacado":false,"descripcion":"","imagen":"assets/products/LA-952366.webp","tags":["marcador","uni","posca","pcf","350","pta","pincel","amarillo"]},{"id":"LA-952353","nombre":"MARCADOR UNI POSCA PCF-350 PTA. PINCEL AZUL","categoria":"Librería","subcategoria":"","precio":10506.28,"destacado":false,"descripcion":"","imagen":"assets/products/LA-952353.webp","tags":["marcador","uni","posca","pcf","350","pta","pincel","azul"]}]}